AntPool/_init_.py
AntPool/antpool.py
solidity_antpool-0.1.1.dist-info/LICENSE
solidity_antpool-0.1.1.dist-info/METADATA
solidity_antpool-0.1.1.dist-info/WHEEL
solidity_antpool-0.1.1.dist-info/top_level.txt
solidity_antpool-0.1.1.dist-info/RECORD
