Metadata-Version: 2.1
Name: solidity-antpool
Version: 0.1.1
Summary: ANTPOOLs application programming interface (API) allows users to access and control their accounts using custom written software.
Home-page: https://github.com/jonova-coder/antpool-solidity
Author: Jordi Pascual Dalmau
Author-email: pascual.dalmau@gmail.com
Classifier: Programming Language :: Python :: 3
Classifier: Operating System :: OS Independent
License-File: LICENSE
Requires-Dist: requests
